rubric_kit/__init__.py
rubric_kit/arena.py
rubric_kit/cli.py
rubric_kit/consensus.py
rubric_kit/converters.py
rubric_kit/execution.py
rubric_kit/generator.py
rubric_kit/llm_judge.py
rubric_kit/main.py
rubric_kit/metrics.py
rubric_kit/output.py
rubric_kit/parser.py
rubric_kit/pdf_export.py
rubric_kit/processor.py
rubric_kit/prompts.py
rubric_kit/schema.py
rubric_kit/tool_evaluator.py
rubric_kit/validator.py
rubric_kit-0.1.6.dist-info/licenses/LICENSE
rubric_kit-0.1.6.dist-info/METADATA
rubric_kit-0.1.6.dist-info/WHEEL
rubric_kit-0.1.6.dist-info/entry_points.txt
rubric_kit-0.1.6.dist-info/top_level.txt
rubric_kit-0.1.6.dist-info/RECORD
