Metadata-Version: 2.4
Name: rubric-kit
Version: 0.1.6
Summary: Generate high-quality Rubrics based on custom dimensions, descriptors, criteria and scoring system.
Author-email: Nicolas Munoz <narmaku@protonmail.com>
Maintainer-email: Nicolas Munoz <narmaku@protonmail.com>
License-Expression: MIT
Project-URL: Homepage, https://github.com/narmaku/rubric-kit
Project-URL: Repository, https://github.com/narmaku/rubric-kit
Project-URL: Issues, https://github.com/narmaku/rubric-kit/issues
Project-URL: Documentation, https://github.com/narmaku/rubric-kit#readme
Keywords: rubric,evaluation,llm,ai,judge,grading,assessment,openai,pydantic,yaml
Classifier: Development Status :: 4 - Beta
Classifier: Intended Audience :: Developers
Classifier: Intended Audience :: Science/Research
Classifier: Operating System :: OS Independent
Classifier: Programming Language :: Python :: 3
Classifier: Programming Language :: Python :: 3.10
Classifier: Programming Language :: Python :: 3.11
Classifier: Programming Language :: Python :: 3.12
Classifier: Topic :: Scientific/Engineering :: Artificial Intelligence
Classifier: Topic :: Software Development :: Libraries :: Python Modules
Classifier: Typing :: Typed
Requires-Python: >=3.10
License-File: LICENSE
Requires-Dist: pydantic>=2.5.0
Requires-Dist: PyYAML>=6.0.1
Requires-Dist: tabulate>=0.9.0
Requires-Dist: litellm>=1.0.0
Requires-Dist: reportlab>=4.0.0
Requires-Dist: matplotlib>=3.7.0
Provides-Extra: dev
Requires-Dist: pytest>=7.4.0; extra == "dev"
Requires-Dist: pytest-cov>=4.1.0; extra == "dev"
Requires-Dist: ruff>=0.8.0; extra == "dev"
Requires-Dist: mypy>=1.13.0; extra == "dev"
Requires-Dist: pre-commit>=4.0.0; extra == "dev"
Requires-Dist: types-PyYAML; extra == "dev"
Requires-Dist: types-tabulate; extra == "dev"
Dynamic: license-file
